[
    {
        "_id": "67dfc754602c0109622c7b0c",
        "key_id": "youtube_e5Oxb69ieJ0",
        "isVideo": true,
        "platform": "youtube",
        "d_source": "y_api",
        "createdAt": "2025-03-23 14:00:50.079000",
        "updatedAt": "2025-03-23 14:00:50.079000",
        "postDate": "2025-03-23 06:11:48",
        "poster_link": "https://i.ytimg.com/vi/e5Oxb69ieJ0/hqdefault.jpg",
        "post_content": {
            "postUri": "e5Oxb69ieJ0",
            "shortcode": "e5Oxb69ieJ0",
            "platform_videoLink": "https://www.youtube.com/watch?v=e5Oxb69ieJ0",
            "platform_viewsCount": 520,
            "platform_dislikesCount": 0,
            "platform_likesCount": 0,
            "caption": "Nagpur Violence | 'Whatever Damage Has Happened...': CM Devendra Fadnavis Vows To Punish Rioters",
            "description": "Maharashtra Chief Minister Devendra Fadnavis said that any damage caused during the violent clashes in Nagpur on March 17 will be recovered from the rioters. \u201cWhatever damage has happened will be recovered from the rioters. If they do not pay the money, then their property will be sold for the recovery. Wherever required, bulldozers will also be used,\u201d said Devendra Fadnavis.\n\n#NagpurViolence #DevendraFadnavis #MaharashtraNews #NagpurRiots #FadnavisOnNagpurViolence #AurangzebTombRow #AurangzebNews \n\nAbout NDTV (English news channel): \n \nNDTV is India's Most-Trusted News Broadcaster with the latest updates in news, sports, entertainment and much more from within India and around the world. Watch big political debates, exclusive entertainment interviews, news bulletins, current affairs, talk shows and tech reviews with our 24x7 news live streams, packed with credible information across all platforms: TV, Internet and Mobile.\n\nFor Latest Videos, click here: https://www.youtube.com/playlist?list=PLYSfYVdrOZvh5iPadUPTAg3sxFD_DZpT_\n\nTo watch NDTV 24x7's premium shows listed together for your easy access, click here: https://www.youtube.com/@NDTV/playlists?view=50&sort=dd&shelf_id=5\n\nFor Ground Reports and Analysis from NDTV's reporters and anchors of day's top news stories, click here: https://www.youtube.com/playlist?list=PLYSfYVdrOZvgHr6OHiZYKbr_21MOmvk04\n\nFor News in Shorts, click here: https://www.youtube.com/playlist?list=PLYSfYVdrOZvjJ8fhLPk_Fz4tFARkpG-Y-\n\nSubscribe to our channel to get latest news updates.\n \nFollow us on Social Media: \nWhatsApp: https://whatsapp.com/channel/0029Va4lixw7z4kcvZI9JM12 \nFacebook: https://www.facebook.com/ndtv/\nTwitter: https://twitter.com/ndtv/   \nInstagram: https://www.instagram.com/ndtv/ \nTelegram Messenger: https://t.me/NDTVbot/?start=hi \n \nFollow us on Google News for Breaking and Latest News Updates:\nNDTV: https://bit.ly/3e5ngbP\nNDTV India (Hindi News): https://bit.ly/3mNVwMY \n \nDownload NDTV Mobile Apps: http://www.ndtv.com/page/apps \n \n#BreakingNews #LatestNews #TodayNews #News #IndiaNews #CurrentAffairs #NDTV",
            "imageList": [
                "https://i.ytimg.com/vi/e5Oxb69ieJ0/default_live.jpg",
                "https://i.ytimg.com/vi/e5Oxb69ieJ0/mqdefault_live.jpg",
                "https://i.ytimg.com/vi/e5Oxb69ieJ0/hqdefault_live.jpg",
                "https://i.ytimg.com/vi/e5Oxb69ieJ0/sddefault_live.jpg",
                "https://i.ytimg.com/vi/e5Oxb69ieJ0/maxresdefault_live.jpg"
            ]
        },
        "privacyStatus": "public",
        "embeddable": true,
        "upvoted_by": [],
        "upvotes_count": 0,
        "downvoted_by": [],
        "downvotes_count": 0,
        "country": [
            "IN"
        ],
        "publisher_id": "ndtv",
        "publisher_name": "NDTV",
        "publisher_profile_pic": "https://yt3.ggpht.com/a/AATXAJxJ_sIpYkNa9wLEDlBNmJQ33onVW53NOgO8Z22a_Fs=s900-c-k-c0x00ffffff-no-rj",
        "publisher_desc": "NDTV is one of the leaders in the production and broadcasting of un-biased and comprehensive news and entertainment programs in India and abroad. \n\nIt offers round-the-clock coverage of latest news and has a unique mix of news bulletins, current affairs, talk shows, and general interest and entertainment programs. \n\nThe company operates NDTV 24X7, an English news channel; NDTV India, a Hindi news channel; and NDTV Profit. NDTV's verticals cover an entire gamut of news and beyond news encompassing recipes, travel, entertainment, shopping, books, health, gadgets and special features. \n\nNDTV delivers reliable information across all platforms: TV, Internet and Mobile. \n\nNDTV broadcasts its programmes in Sri Lanka,  Bangladesh, Maldives, Nepal, Middle East, Mauritius, South Africa, Europe, US, Canada & ANZ.",
        "publisher_country": [
            "IN"
        ]
    }
]