[
    {
        "key_id": "UCEH7P7kyJIkS_gJf93VYbmg/live_494184",
        "isVisible": true,
        "stream_id": "twitch_314281379690",
        "channel_name": "Quackasper",
        "game_name": "Mobile Legends: Bang Bang",
        "category": "gaming",
        "platform": "twitch",
        "createdAt": "2025-04-21 14:24:10.013000",
        "updatedAt": "2025-04-21 14:32:22.208000",
        "postDate": "2025-04-21T08:45:08Z",
        "stream_poster_link": "https://static-cdn.jtvnw.net/previews-ttv/live_user_quackasper-640x480.jpg",
        "game_poster_link": "https://static-cdn.jtvnw.net/ttv-boxart/494184_IGDB-640x480.jpg",
        "post_content": {
            "platform_videoLink": "https://www.twitch.tv/Quackasper",
            "platform_viewsCount": 8,
            "platform_likesCount": 0,
            "platform_dislikesCount": 0,
            "caption": "[FIL/ENG] Mobile Legends Practice with trippings \ud83e\udd86",
            "description": "[FIL/ENG] Mobile Legends Practice with trippings \ud83e\udd86"
        },
        "popularityScore": 0.9942043122450531,
        "downvotes_count": 0,
        "downvoted_by": [],
        "upvotes_count": 0,
        "upvoted_by": [],
        "country": [
            "WW"
        ],
        "related_streams": [],
        "isNative": false
    }
]